{
    "frontend": [
        {
            "id": "ReactJS",
            "title": "React",
            "level": 5
        },
        {
            "id": "VueJS",
            "title": "Vue",
            "level": 4
        },
        {
            "id": "bootstrap",
            "title": "Bootstrap",
            "level": 4
        },
        {
            "id": "tailWind",
            "title": "Tailwind CSS",
            "level": 5
        },
        {
            "id": "SCSS",
            "title": "SCSS",
            "level": 5
        },
        {
            "id": "Jquery",
            "title": "JQuery",
            "level": 4
        }
    ],
    "mobile": [
        {
            "id": "reactnative",
            "title": "React Native",
            "level": 4
        }
    ],
    "backend": [
        {
            "id": "nodejs",
            "title": "Node JS",
            "level": 5
        },
        {
            "id": "dotnet",
            "title": ".Net Core",
            "level": 5
        },
        {
            "id": "cms",
            "title": "Headless CMS",
            "level": 5
        },
        {
            "id": "sqlServer",
            "title": "SQL Server",
            "level": 4
        },
        {
            "id": "sql",
            "title": "mySQL",
            "level": 4
        }
    ],
    "devops": [
        {
            "id": "aws",
            "title": "Amazon Web Services",
            "level": 5
        },
        {
            "id": "git",
            "title": "Git",
            "level": 4
        },
        {
            "id": "bitbucket",
            "title": "Bitbucket",
            "level": 4
        },
        {
            "id": "octopusDeploy",
            "title": "Octopus Deploy",
            "level": 4
        },
        {
            "id": "kubernetes",
            "title": "Kubernetes",
            "level": 3
        }
    ],
    "language": [
        {
            "id": "vietnamese",
            "title": "Vietnamese",
            "level": 5
        },
        {
            "id": "en",
            "title": "English",
            "level": 4
        }
    ]
}